pypefilter/__init__.py
pypefilter/pypefilter.py
pypefilter-0.0.5.dist-info/LICENSE
pypefilter-0.0.5.dist-info/METADATA
pypefilter-0.0.5.dist-info/WHEEL
pypefilter-0.0.5.dist-info/entry_points.txt
pypefilter-0.0.5.dist-info/top_level.txt
pypefilter-0.0.5.dist-info/RECORD
