Metadata-Version: 2.1
Name: pypefilter
Version: 0.0.5
Summary: PyPEfilter filters out non-native Portable Executable
Home-page: https://github.com/packmad/pypefilter
Author: Simone Aonzo
Author-email: simone.aonzo@gmail.com
License: UNKNOWN
Platform: UNKNOWN
Classifier: Programming Language :: Python :: 3
Classifier: License :: OSI Approved :: MIT License
Classifier: Operating System :: OS Independent
Requires-Python: >=3.6
Requires-Dist: python-magic
